leanautomation/__init__.py
leanautomation/_http.py
leanautomation/client.py
leanautomation/admin/domain.py
leanautomation/admin/item/__init__.py
leanautomation/admin/item/item.py
leanautomation/admin/item/types.py
leanautomation/admin/tenant/__init__.py
leanautomation/admin/tenant/tenant.py
leanautomation/admin/workspace/__init__.py
leanautomation/admin/workspace/adminworkspace.py
leanautomation/auth/__init__.py
leanautomation/auth/auth.py
leanautomation/auth/scopes.py
leanautomation/core/__init__.py
leanautomation/core/capacity/__init__.py
leanautomation/core/capacity/capacity.py
leanautomation/core/gateway/gateway.py
leanautomation/core/git/git.py
leanautomation/core/item/__init__.py
leanautomation/core/item/item.py
leanautomation/core/jobscheduler/jobscheduler.py
leanautomation/core/workspace/__init__.py
leanautomation/core/workspace/identity.py
leanautomation/core/workspace/role.py
leanautomation/core/workspace/workspace.py
leanautomation/dataactivator/__init__.py
leanautomation/dataactivator/reflex/__init__.py
leanautomation/dataengineering/__init__.py
leanautomation/dataengineering/lakehouse.py
leanautomation/dataengineering/notebook.py
leanautomation/dataengineering/sqlendpoints.py
leanautomation/datafactory/__init__.py
leanautomation/datafactory/datapipeline.py
leanautomation/datascience/__init__.py
leanautomation/datawarehouse/__init__.py
leanautomation/datawarehouse/mirroredwarehouse.py
leanautomation/datawarehouse/warehouse.py
leanautomation/industrysolutions/__init__.py
leanautomation/models/__init__.py
leanautomation/models/adminworkspace.py
leanautomation/models/capacity.py
leanautomation/models/dashboard.py
leanautomation/models/datamart.py
leanautomation/models/datapipeline.py
leanautomation/models/domain.py
leanautomation/models/eventhouse.py
leanautomation/models/eventstream.py
leanautomation/models/gateway.py
leanautomation/models/git.py
leanautomation/models/item.py
leanautomation/models/jobscheduler.py
leanautomation/models/kqldatabase.py
leanautomation-0.1.9.dist-info/licenses/LICENSE
leanautomation-0.1.9.dist-info/METADATA
leanautomation-0.1.9.dist-info/WHEEL
leanautomation-0.1.9.dist-info/top_level.txt
leanautomation-0.1.9.dist-info/RECORD
